aws_google_auth/__init__.py
aws_google_auth/_version.py
aws_google_auth/amazon.py
aws_google_auth/configuration.py
aws_google_auth/google.py
aws_google_auth/u2f.py
aws_google_auth/util.py
aws_google_auth/tests/__init__.py
aws_google_auth/tests/test_amazon.py
aws_google_auth/tests/test_args_parser.py
aws_google_auth/tests/test_backwards_compatibility.py
aws_google_auth/tests/test_config_parser.py
aws_google_auth/tests/test_configuration.py
aws_google_auth/tests/test_configuration_persistence.py
aws_google_auth/tests/test_google.py
aws_google_auth/tests/test_init.py
aws_google_auth/tests/test_python_version.py
aws_google_auth/tests/test_util.py
aws_google_auth-0.0.38.dist-info/LICENSE.txt
aws_google_auth-0.0.38.dist-info/METADATA
aws_google_auth-0.0.38.dist-info/WHEEL
aws_google_auth-0.0.38.dist-info/entry_points.txt
aws_google_auth-0.0.38.dist-info/top_level.txt
aws_google_auth-0.0.38.dist-info/RECORD
