Metadata-Version: 2.1
Name: aws-google-auth
Version: 0.0.38
Summary: Acquire AWS STS (temporary) credentials via Google Apps SAML Single Sign On
Home-page: https://github.com/cevoaustralia/aws-google-auth
Author: Colin Panisset
Author-email: colin.panisset@cevo.com.au
License: MIT
Download-URL: https://github.com/cevoaustralia/aws-google-auth/archive/0.0.38.tar.gz
Keywords: saml sso federated identity google aws cli
Platform: UNKNOWN
Classifier: Development Status :: 3 - Alpha
Classifier: Intended Audience :: Developers
Classifier: Intended Audience :: System Administrators
Classifier: Topic :: Security
Classifier: Topic :: System :: Systems Administration :: Authentication/Directory
Classifier: License :: OSI Approved :: MIT License
Classifier: Programming Language :: Python :: 2
Classifier: Programming Language :: Python :: 2.6
Classifier: Programming Language :: Python :: 2.7
License-File: LICENSE.txt
Requires-Dist: beautifulsoup4
Requires-Dist: boto3
Requires-Dist: configparser
Requires-Dist: filelock
Requires-Dist: keyring
Requires-Dist: keyrings.alt
Requires-Dist: lxml
Requires-Dist: Pillow
Requires-Dist: requests
Requires-Dist: six
Requires-Dist: tabulate
Requires-Dist: tzlocal
Provides-Extra: u2f
Requires-Dist: python-u2flib-host ; extra == 'u2f'
